file_chat_input/__init__.py
file_chat_input/frontend/build/asset-manifest.json
file_chat_input/frontend/build/bootstrap.min.css
file_chat_input/frontend/build/index.html
file_chat_input/frontend/build/static/css/main.fa1eef00.css
file_chat_input/frontend/build/static/css/main.fa1eef00.css.map
file_chat_input/frontend/build/static/js/main.26e32e16.js
file_chat_input/frontend/build/static/js/main.26e32e16.js.LICENSE.txt
file_chat_input/frontend/build/static/js/main.26e32e16.js.map
file_chat_input-0.0.2.dist-info/LICENSE
file_chat_input-0.0.2.dist-info/METADATA
file_chat_input-0.0.2.dist-info/WHEEL
file_chat_input-0.0.2.dist-info/top_level.txt
file_chat_input-0.0.2.dist-info/RECORD
